odoo/addons/vertical_carsharing_rest_api/__init__.py
odoo/addons/vertical_carsharing_rest_api/__manifest__.py
odoo/addons/vertical_carsharing_rest_api/services/__init__.py
odoo/addons/vertical_carsharing_rest_api/services/schemas.py
odoo/addons/vertical_carsharing_rest_api/services/services_res_partner.py
odoo12_addon_vertical_carsharing_rest_api-12.0.0.0.2.dist-info/METADATA
odoo12_addon_vertical_carsharing_rest_api-12.0.0.0.2.dist-info/WHEEL
odoo12_addon_vertical_carsharing_rest_api-12.0.0.0.2.dist-info/top_level.txt
odoo12_addon_vertical_carsharing_rest_api-12.0.0.0.2.dist-info/RECORD
