Metadata-Version: 2.1
Name: odoo12-addon-vertical-carsharing-rest-api
Version: 12.0.0.0.2
Summary: Partner rest service
Home-page: https://www.sommobilitat.coop
Author: Som Mobilitat
License: UNKNOWN
Platform: UNKNOWN
Classifier: Programming Language :: Python
Classifier: Framework :: Odoo
Classifier: Framework :: Odoo :: 12.0
Requires-Python: >=3.5
Requires-Dist: odoo12-addon-easy-my-coop-api
Requires-Dist: odoo <12.1dev,>=12.0a
